CodeBat/CodeBat.py
CodeBat/__init__.py
CodeBat-0.2.1.dist-info/LICENSE.txt
CodeBat-0.2.1.dist-info/METADATA
CodeBat-0.2.1.dist-info/WHEEL
CodeBat-0.2.1.dist-info/top_level.txt
CodeBat-0.2.1.dist-info/RECORD
